airrun/__init__.py
airrun/__main__.py
airrun/config.py
airrun/main.py
airrun/record.py
airrun/runner.py
airrun/template.py
airrun/cli/__init__.py
airrun/cli/__init__.pyc
airrun/cli/__main__.py
airrun/cli/__main__.pyc
airrun/cli/info.py
airrun/cli/parser.py
airrun/cli/parser.pyc
airrun/cli/__pycache__/__init__.cpython-37.pyc
airrun/cli/__pycache__/__main__.cpython-37.pyc
airrun/cli/__pycache__/parser.cpython-37.pyc
airrun/common/__init__.py
airrun/common/base.py
airrun/common/command_helper.py
airrun/common/device.py
airrun/common/exception.py
airrun/common/helper.py
airrun/common/marks.py
airrun/common/queue.py
airrun/report/__init__.py
airrun/report/__init__.pyc
airrun/report/log_template.html
airrun/report/report.py
airrun/report/__pycache__/__init__.cpython-37.pyc
airrun/report/__pycache__/report.cpython-37.pyc
airrun/report/css/monokai_sublime.min.css
airrun/report/css/report.css
airrun/report/fonts/SourceHanSansCN-Regular.ttf
airrun/report/fonts/glyphicons-halflings-regular.eot
airrun/report/fonts/glyphicons-halflings-regular.svg
airrun/report/fonts/glyphicons-halflings-regular.ttf
airrun/report/fonts/glyphicons-halflings-regular.woff
airrun/report/fonts/glyphicons-halflings-regular.woff2
airrun/report/image/AirLab.png
airrun/report/image/Airtest.png
airrun/report/image/AirtestIDE.png
airrun/report/image/arrow.png
airrun/report/image/back.svg
airrun/report/image/broken.png
airrun/report/image/close.svg
airrun/report/image/console_hover.svg
airrun/report/image/console_normal.svg
airrun/report/image/copy.svg
airrun/report/image/download_log.svg
airrun/report/image/eye.svg
airrun/report/image/fail.svg
airrun/report/image/less.svg
airrun/report/image/maximize.svg
airrun/report/image/minimize.svg
airrun/report/image/more.svg
airrun/report/image/netease.png
airrun/report/image/open_in_new_tab.svg
airrun/report/image/order.svg
airrun/report/image/poco.png
airrun/report/image/step_fail.svg
airrun/report/image/step_success.svg
airrun/report/image/success.svg
airrun-0.0.2.dist-info/LICENSE
airrun-0.0.2.dist-info/METADATA
airrun-0.0.2.dist-info/WHEEL
airrun-0.0.2.dist-info/top_level.txt
airrun-0.0.2.dist-info/RECORD
